<annotation>
	<folder>train</folder>
	<filename>57_94D.jpg</filename>
	<path>E:\Projects\PyCaptchaBreaker\model training\CAPTCHA_images\train\57_94D.jpg</path>
	<source>
		<database>Unknown</database>
	</source>
	<size>
		<width>750</width>
		<height>200</height>
		<depth>3</depth>
	</size>
	<segmented>0</segmented>
	<object>
		<name>9</name>
		<pose>Unspecified</pose>
		<truncated>0</truncated>
		<difficult>0</difficult>
		<bndbox>
			<xmin>74</xmin>
			<ymin>73</ymin>
			<xmax>168</xmax>
			<ymax>175</ymax>
		</bndbox>
	</object>
	<object>
		<name>4</name>
		<pose>Unspecified</pose>
		<truncated>0</truncated>
		<difficult>0</difficult>
		<bndbox>
			<xmin>201</xmin>
			<ymin>66</ymin>
			<xmax>286</xmax>
			<ymax>172</ymax>
		</bndbox>
	</object>
	<object>
		<name>D</name>
		<pose>Unspecified</pose>
		<truncated>0</truncated>
		<difficult>0</difficult>
		<bndbox>
			<xmin>280</xmin>
			<ymin>68</ymin>
			<xmax>376</xmax>
			<ymax>168</ymax>
		</bndbox>
	</object>
</annotation>
